whisper_mic/__init__.py
whisper_mic/cli.py
whisper_mic/mic.py
whisper_voice_commands-0.0.6.dist-info/LICENSE
whisper_voice_commands-0.0.6.dist-info/METADATA
whisper_voice_commands-0.0.6.dist-info/WHEEL
whisper_voice_commands-0.0.6.dist-info/entry_points.txt
whisper_voice_commands-0.0.6.dist-info/top_level.txt
whisper_voice_commands-0.0.6.dist-info/RECORD
