Metadata-Version: 2.1
Name: whisper-voice-commands
Version: 0.0.6
Summary: Execute scripts with Whisper for your microphone
Author-email: Deven B-L <deven.boutin@gmail.com>, Blake Mallory <blakecmallory@gmail.com>
Project-URL: Homepage, https://github.com/DevenBL/whisper_mic_exec/tree/Whisper-Voice-Commands
Project-URL: Bug Tracker, https://github.com/DevenBL/whisper_mic_exec/tree/Whisper-Voice-Commands/issues
Classifier: Programming Language :: Python :: 3
Classifier: License :: OSI Approved :: MIT License
Classifier: Operating System :: OS Independent
Requires-Python: >=3.9
License-File: LICENSE
Requires-Dist: speechrecognition
Requires-Dist: pyaudio
Requires-Dist: pydub
Requires-Dist: requests
Requires-Dist: pydantic
Requires-Dist: attrs
Requires-Dist: numpy
Requires-Dist: tdqm
Requires-Dist: more-itertools
Requires-Dist: transformers
Requires-Dist: torch
Requires-Dist: ffmpeg-python
Requires-Dist: click
Requires-Dist: openai-whisper
Requires-Dist: importlib-metadata ; python_version > "3.9"
